shipchain_common/__init__.py
shipchain_common/authentication.py
shipchain_common/aws.py
shipchain_common/custom_logging/__init__.py
shipchain_common/custom_logging/filter.py
shipchain_common/custom_logging/middleware.py
shipchain_common/exceptions.py
shipchain_common/filters.py
shipchain_common/iot.py
shipchain_common/mixins.py
shipchain_common/pagination.py
shipchain_common/permissions.py
shipchain_common/renderers.py
shipchain_common/routers.py
shipchain_common/rpc.py
shipchain_common/serializers.py
shipchain_common/test_utils/__init__.py
shipchain_common/test_utils/helpers.py
shipchain_common/test_utils/httpretty_asserter.py
shipchain_common/test_utils/json_asserter.py
shipchain_common/test_utils/mocked_rpc_responses.py
shipchain_common/utils.py
shipchain_common/viewsets.py
shipchain_common-1.0.29.dist-info/LICENSE
shipchain_common-1.0.29.dist-info/WHEEL
shipchain_common-1.0.29.dist-info/METADATA
shipchain_common-1.0.29.dist-info/RECORD
